<KicadtoNgspice><source><v3 name="Source type">pulse<field1 name="Initial Value">0</field1><field2 name="Pulse Value">5</field2><field3 name="Delay Time">0.1m</field3><field4 name="Rise Time">0.1m</field4><field5 name="Fall Time">0.1m</field5><field5 name="Pulse width">32</field5><field5 name="Period">64</field5></v3><v9 name="Source type">pulse<field1 name="Initial Value">0</field1><field2 name="Pulse Value">5</field2><field3 name="Delay Time">0.1m</field3><field4 name="Rise Time">0.1m</field4><field5 name="Fall Time">0.1m</field5><field5 name="Pulse width">1</field5><field5 name="Period">2</field5></v9><v7 name="Source type">pulse<field1 name="Initial Value">0</field1><field2 name="Pulse Value">5</field2><field3 name="Delay Time">0.1m</field3><field4 name="Rise Time">0.1m</field4><field5 name="Fall Time">0.1m</field5><field5 name="Pulse width">2</field5><field5 name="Period">4</field5></v7><v6 name="Source type">pulse<field1 name="Initial Value">0</field1><field2 name="Pulse Value">5</field2><field3 name="Delay Time">0.1m</field3><field4 name="Rise Time">0.1m</field4><field5 name="Fall Time">0.1m</field5><field5 name="Pulse width">4</field5><field5 name="Period">8</field5></v6><v5 name="Source type">pulse<field1 name="Initial Value">0</field1><field2 name="Pulse Value">5</field2><field3 name="Delay Time">0.1m</field3><field4 name="Rise Time">0.1m</field4><field5 name="Fall Time">0.1m</field5><field5 name="Pulse width">8</field5><field5 name="Period">16</field5></v5><v4 name="Source type">pulse<field1 name="Initial Value">0</field1><field2 name="Pulse Value">5</field2><field3 name="Delay Time">0.1m</field3><field4 name="Rise Time">0.1m</field4><field5 name="Fall Time">0.1m</field5><field5 name="Pulse width">16</field5><field5 name="Period">32</field5></v4><v2 name="Source type">pulse<field1 name="Initial Value">0</field1><field2 name="Pulse Value">5</field2><field3 name="Delay Time">0.1m</field3><field4 name="Rise Time">0.1m</field4><field5 name="Fall Time">0.1m</field5><field5 name="Pulse width">64</field5><field5 name="Period">128</field5></v2><v1 name="Source type">pulse<field1 name="Initial Value">0</field1><field2 name="Pulse Value">1.8</field2><field3 name="Delay Time">0.1m</field3><field4 name="Rise Time">0.1m</field4><field5 name="Fall Time">0.1m</field5><field5 name="Pulse width">128</field5><field5 name="Period">256</field5></v1><v8 name="Source type">pulse<field1 name="Initial Value">0</field1><field2 name="Pulse Value">5</field2><field3 name="Delay Time">0.1m</field3><field4 name="Rise Time">0.1m</field4><field5 name="Fall Time">0.1m</field5><field5 name="Pulse width">1</field5><field5 name="Period">2</field5></v8><v10 name="Source type">pulse<field1 name="Initial Value">0</field1><field2 name="Pulse Value">5</field2><field3 name="Delay Time">0.1m</field3><field4 name="Rise Time">0.1m</field4><field5 name="Fall Time">0.1m</field5><field5 name="Pulse width">2</field5><field5 name="Period">4</field5></v10><v12 name="Source type">pulse<field1 name="Initial Value">0</field1><field2 name="Pulse Value">5</field2><field3 name="Delay Time">0.1m</field3><field4 name="Rise Time">0.1m</field4><field5 name="Fall Time">0.1m</field5><field5 name="Pulse width">4</field5><field5 name="Period">8</field5></v12><v11 name="Source type">pulse<field1 name="Initial Value">0</field1><field2 name="Pulse Value">5</field2><field3 name="Delay Time">0.1m</field3><field4 name="Rise Time">0.1m</field4><field5 name="Fall Time">0.1m</field5><field5 name="Pulse width">8</field5><field5 name="Period">16</field5></v11><v13 name="Source type">pulse<field1 name="Initial Value">0</field1><field2 name="Pulse Value">5</field2><field3 name="Delay Time">0.1m</field3><field4 name="Rise Time">0.1m</field4><field5 name="Fall Time">0.1m</field5><field5 name="Pulse width">1</field5><field5 name="Period">2</field5></v13><v1 name="Source type">dc<field1 name="Value">5</field1></v1><v11 name="Source type">dc<field1 name="Value">5</field1></v11><v10 name="Source type">dc<field1 name="Value">5</field1></v10><v8 name="Source type">dc<field1 name="Value">5</field1></v8><v12 name="Source type">dc<field1 name="Value">5</field1></v12></source><model><u13 name="type">glenn_ram128x32<field1 name="Enter Rise Delay (default=1.0e-9)" /><field2 name="Enter Fall Delay (default=1.0e-9)" /><field3 name="Enter Input Load (default=1.0e-12)" /><field4 name="Enter Instance ID (Between 0-99)" /></u13><u19 name="type">adc_bridge<field5 name="Enter value for in_low (default=1.0)" /><field6 name="Enter value for in_high (default=2.0)" /><field7 name="Enter Rise Delay (default=1.0e-9)" /><field8 name="Enter Fall Delay (default=1.0e-9)" /></u19><u16 name="type">adc_bridge<field9 name="Enter value for in_low (default=1.0)" /><field10 name="Enter value for in_high (default=2.0)" /><field11 name="Enter Rise Delay (default=1.0e-9)" /><field12 name="Enter Fall Delay (default=1.0e-9)" /></u16><u20 name="type">adc_bridge<field13 name="Enter value for in_low (default=1.0)" /><field14 name="Enter value for in_high (default=2.0)" /><field15 name="Enter Rise Delay (default=1.0e-9)" /><field16 name="Enter Fall Delay (default=1.0e-9)" /></u20><u15 name="type">adc_bridge<field17 name="Enter value for in_low (default=1.0)" /><field18 name="Enter value for in_high (default=2.0)" /><field19 name="Enter Rise Delay (default=1.0e-9)" /><field20 name="Enter Fall Delay (default=1.0e-9)" /></u15><u18 name="type">adc_bridge<field21 name="Enter value for in_low (default=1.0)" /><field22 name="Enter value for in_high (default=2.0)" /><field23 name="Enter Rise Delay (default=1.0e-9)" /><field24 name="Enter Fall Delay (default=1.0e-9)" /></u18><u14 name="type">adc_bridge<field25 name="Enter value for in_low (default=1.0)" /><field26 name="Enter value for in_high (default=2.0)" /><field27 name="Enter Rise Delay (default=1.0e-9)" /><field28 name="Enter Fall Delay (default=1.0e-9)" /></u14><u21 name="type">dac_bridge<field29 name="Enter value for out_low (default=0.0)" /><field30 name="Enter value for out_high (default=5.0)" /><field31 name="Enter value for out_undef (default=0.5)" /><field32 name="Enter value for input load (default=1.0e-12)" /><field33 name="Enter the Rise Time (default=1.0e-9)" /><field34 name="Enter the Fall Time (default=1.0e-9)" /></u21><u28 name="type">dac_bridge<field35 name="Enter value for out_low (default=0.0)" /><field36 name="Enter value for out_high (default=5.0)" /><field37 name="Enter value for out_undef (default=0.5)" /><field38 name="Enter value for input load (default=1.0e-12)" /><field39 name="Enter the Rise Time (default=1.0e-9)" /><field40 name="Enter the Fall Time (default=1.0e-9)" /></u28><u22 name="type">dac_bridge<field41 name="Enter value for out_low (default=0.0)" /><field42 name="Enter value for out_high (default=5.0)" /><field43 name="Enter value for out_undef (default=0.5)" /><field44 name="Enter value for input load (default=1.0e-12)" /><field45 name="Enter the Rise Time (default=1.0e-9)" /><field46 name="Enter the Fall Time (default=1.0e-9)" /></u22><u29 name="type">dac_bridge<field47 name="Enter value for out_low (default=0.0)" /><field48 name="Enter value for out_high (default=5.0)" /><field49 name="Enter value for out_undef (default=0.5)" /><field50 name="Enter value for input load (default=1.0e-12)" /><field51 name="Enter the Rise Time (default=1.0e-9)" /><field52 name="Enter the Fall Time (default=1.0e-9)" /></u29></model><devicemodel /><subcircuit /><analysis><ac><field1 name="Lin">true</field1><field2 name="Dec">false</field2><field3 name="Oct">false</field3><field4 name="Start Frequency" /><field5 name="Stop Frequency" /><field6 name="No. of points" /><field7 name="Start Fre Combo">Hz</field7><field8 name="Stop Fre Combo">Hz</field8></ac><dc><field1 name="Source 1" /><field2 name="Start" /><field3 name="Increment" /><field4 name="Stop" /><field5 name="Operating Point">0</field5><field6 name="Start Combo">Volts or Amperes</field6><field7 name="Increment Combo">Volts or Amperes</field7><field8 name="Stop Combo">Volts or Amperes</field8><field9 name="Source 2" /><field10 name="Start" /><field11 name="Increment" /><field12 name="Stop" /><field13 name="Start Combo">Volts or Amperes</field13><field14 name="Increment Combo">Volts or Amperes</field14><field15 name="Stop Combo">Volts or Amperes</field15></dc><tran><field1 name="Start Time">1</field1><field2 name="Step Time">.1</field2><field3 name="Stop Time">512</field3><field4 name="Start Combo">Sec</field4><field5 name="Step Combo">Sec</field5><field6 name="Stop Combo">Sec</field6></tran></analysis></KicadtoNgspice>